ml_report_kit/__init__.py
ml_report_kit/report.py
ml_report_kit-0.1.4.dist-info/METADATA
ml_report_kit-0.1.4.dist-info/WHEEL
ml_report_kit-0.1.4.dist-info/licenses/LICENSE
ml_report_kit-0.1.4.dist-info/RECORD
