Metadata-Version: 2.3
Name: ml-report-kit
Version: 0.1.4
Summary: Generating evaluating metrics reports for machine learning models in two lines of code.
Project-URL: Homepage, https://github.com/davidsbatista/ml-report-kit
Author-email: "David S. Batista" <dsbatista@gmail.com>
License: MIT
License-File: LICENSE
Classifier: License :: OSI Approved :: MIT License
Classifier: Operating System :: OS Independent
Classifier: Programming Language :: Python :: 3
Requires-Python: >=3.9
Requires-Dist: matplotlib
Requires-Dist: pandas
Requires-Dist: scikit-learn
Provides-Extra: dev
Requires-Dist: pytest; extra == 'dev'
